zzy_schedule_quality/__init__.py
zzy_schedule_quality/service/quality.py
zzy_schedule_quality/utils/constant.py
zzy_schedule_quality-0.1.3.dist-info/WHEEL
zzy_schedule_quality-0.1.3.dist-info/entry_points.txt
zzy_schedule_quality-0.1.3.dist-info/METADATA
zzy_schedule_quality-0.1.3.dist-info/RECORD
