Metadata-Version: 2.3
Name: zzy-schedule-quality
Version: 0.1.3
Summary: Add your description here
Author: yanggy
Author-email: yanggy <863007116@qq.com>
Requires-Dist: mcp[cli]>=1.17.0
Requires-Dist: requests>=2.31.0
Requires-Python: >=3.12
